cyclarity_sdk/expert_builder/__init__.py
cyclarity_sdk/expert_builder/runnable/__init__.py
cyclarity_sdk/expert_builder/runnable/run_from_cli.py
cyclarity_sdk/expert_builder/runnable/runnable.py
cyclarity_sdk/expert_builder/runnable/runnable_usage_example.py
cyclarity_sdk/platform_api/Iplatform_connector.py
cyclarity_sdk/platform_api/__init__.py
cyclarity_sdk/platform_api/connectors/__init__.py
cyclarity_sdk/platform_api/connectors/cli_connector.py
cyclarity_sdk/platform_api/exceptions.py
cyclarity_sdk/platform_api/logger/__init__.py
cyclarity_sdk/platform_api/logger/clarity_streamer.py
cyclarity_sdk/platform_api/logger/integrated_logging.py
cyclarity_sdk/platform_api/logger/models.py
cyclarity_sdk/platform_api/platform_api.py
cyclarity_sdk/platform_api/types.py
cyclarity_sdk/sdk_models/__init__.py
cyclarity_sdk/sdk_models/artifacts/__init__.py
cyclarity_sdk/sdk_models/artifacts/models.py
cyclarity_sdk/sdk_models/artifacts/types.py
cyclarity_sdk/sdk_models/findings/__init__.py
cyclarity_sdk/sdk_models/findings/models.py
cyclarity_sdk/sdk_models/findings/types.py
cyclarity_sdk/sdk_models/models.py
cyclarity_sdk/sdk_models/types.py
cyclarity_sdk-1.0.93.dist-info/METADATA
cyclarity_sdk-1.0.93.dist-info/WHEEL
cyclarity_sdk-1.0.93.dist-info/RECORD
